IvmDriver/DFTMatrix.spec
IvmDriver/Dockerfile
IvmDriver/Matrixgui.py
IvmDriver/__init__.py
IvmDriver/appexe.spec
IvmDriver/driver.py
IvmDriver/driver.ui
IvmDriver/driverPage.py
IvmDriver/exeGenerate.py
IvmDriver/fileopen.py
IvmDriver/logger.py
IvmDriver/mainDriver.spec
IvmDriver/matrix.py
IvmDriver/matrixDriver.py
IvmDriver/matrixFrame.ui
IvmDriver/mcp2221.py
IvmDriver/mcp2317.py
IvmDriver/reserach.ipynb
IvmDriver/signalRoot.py
IvmDriver/GPIOExpander/pcf8547.py
IvmDriver/assets/logo.ico
IvmDriver/assets/logo.png
IvmDriver/docs/DFT Matrix.pptx
IvmDriver/docs/MCP23017-Data-Sheet-DS20001952.pdf
IvmDriver/docs/expand-2-click-manual-v100-1484105.pdf
IvmDriver/signals/SignalConfig.json
IvmDriver/signals/dummysignalconfig.json
IvmDriver/signals/dummysignalconfig1.json
IvmDriver/signals/intrepretor.json
IvmDriver/signals/signalConfigtest.json
IvmDriver/signals/signalroot_matrix.json
IvmDriver/signals/signalroot_matrix1.json
IvmDriver/styles/app.qss
IvmDriver/styles/scrollAreaFrame.qss
IvmDriver-0.0.9.data/data/DFT Matrix.pptx
IvmDriver-0.0.9.data/data/DFTMatrix.spec
IvmDriver-0.0.9.data/data/Dockerfile
IvmDriver-0.0.9.data/data/MCP23017-Data-Sheet-DS20001952.pdf
IvmDriver-0.0.9.data/data/Matrixgui.py
IvmDriver-0.0.9.data/data/SignalConfig.json
IvmDriver-0.0.9.data/data/__init__.py
IvmDriver-0.0.9.data/data/app.qss
IvmDriver-0.0.9.data/data/appexe.spec
IvmDriver-0.0.9.data/data/driver.py
IvmDriver-0.0.9.data/data/driver.ui
IvmDriver-0.0.9.data/data/driverPage.py
IvmDriver-0.0.9.data/data/dummysignalconfig.json
IvmDriver-0.0.9.data/data/dummysignalconfig1.json
IvmDriver-0.0.9.data/data/exeGenerate.py
IvmDriver-0.0.9.data/data/expand-2-click-manual-v100-1484105.pdf
IvmDriver-0.0.9.data/data/fileopen.py
IvmDriver-0.0.9.data/data/intrepretor.json
IvmDriver-0.0.9.data/data/logger.py
IvmDriver-0.0.9.data/data/logo.ico
IvmDriver-0.0.9.data/data/logo.png
IvmDriver-0.0.9.data/data/mainDriver.spec
IvmDriver-0.0.9.data/data/matrix.py
IvmDriver-0.0.9.data/data/matrixDriver.py
IvmDriver-0.0.9.dist-info/METADATA
IvmDriver-0.0.9.dist-info/WHEEL
IvmDriver-0.0.9.dist-info/top_level.txt
IvmDriver-0.0.9.dist-info/RECORD
