Metadata-Version: 2.1
Name: IvmDriver
Version: 0.0.9
Home-page: https://github.com/HarishKumarSedu/matrix
Author: HarishKumarSedu
Author-email: harishkumarsedu@gmail.com
Project-URL: Bug Tracker, https://github.com/HarishKumarSedu/matrix/issues
Requires-Dist: pymcp2221a
Requires-Dist: pyqt5
Requires-Dist: setuptools
Requires-Dist: pathlib
Requires-Dist: PyVISA
Requires-Dist: rich
